touchlab_comm_py/__init__.py
touchlab_comm_py/examples/example.py
touchlab_comm_py/examples/example_flash.py
touchlab_comm_py/examples/example_translate.py
touchlab_comm_py/touchlab_comm_py.cp313-win_amd64.pyd
touchlab_comm_py-0.2.0.dist-info/METADATA
touchlab_comm_py-0.2.0.dist-info/WHEEL
touchlab_comm_py-0.2.0.dist-info/licenses/LICENSE.txt
touchlab_comm_py-0.2.0.dist-info/RECORD
