Metadata-Version: 2.4
Name: touchlab_comm_py
Version: 0.2.0
Summary: Touchlab Driver Python Bindings
Keywords: touchlab,communication,serial
Author-Email: Vladimir Ivan <vlad@touchlab.com>
License-Expression: LicenseRef-Touchlab
License-File: LICENSE.txt
Classifier: Programming Language :: Python :: 3 :: Only
Classifier: Programming Language :: Python :: 3.8
Classifier: Programming Language :: Python :: 3.9
Classifier: Programming Language :: Python :: 3.10
Classifier: Programming Language :: Python :: 3.11
Classifier: Programming Language :: Python :: 3.12
Classifier: Programming Language :: Python :: 3.13
Project-URL: Homepage, https://touchlab-avatarx.github.io/touchlab_driver_py
Project-URL: Documentation, https://touchlab-avatarx.github.io/touchlab_driver_py/api.html
Requires-Python: >=3.8
Provides-Extra: test
Requires-Dist: pytest>=6.0; extra == "test"
